pipen_cli_require/__init__.py
pipen_cli_require/entry.py
pipen_cli_require/require.py
pipen_cli_require/version.py
pipen_cli_require-1.0.2.dist-info/METADATA
pipen_cli_require-1.0.2.dist-info/WHEEL
pipen_cli_require-1.0.2.dist-info/entry_points.txt
pipen_cli_require-1.0.2.dist-info/RECORD
